basicallybars/__init__.py
basicallybars-1.0.1.dist-info/METADATA
basicallybars-1.0.1.dist-info/WHEEL
basicallybars-1.0.1.dist-info/licenses/LICENCE
basicallybars-1.0.1.dist-info/RECORD
