Metadata-Version: 2.1
Name: basicallybars
Version: 1.0.1
Summary: A visual way to display algorithm status.
Project-URL: Github, https://github.com/Coder2354/basicallybars/tree/master
Author-email: Sleepy82 <shgj7y1z@duck.com>
License-File: LICENCE
Classifier: License :: OSI Approved :: MIT License
Classifier: Operating System :: OS Independent
Classifier: Programming Language :: Python :: 3
Requires-Python: >=3.6
